magali/__init__.py
magali/_version.py
magali/_version_generated.py
magali/tests/__init__.py
magali-0.0.post13.dist-info/LICENSE.txt
magali-0.0.post13.dist-info/METADATA
magali-0.0.post13.dist-info/WHEEL
magali-0.0.post13.dist-info/top_level.txt
magali-0.0.post13.dist-info/zip-safe
magali-0.0.post13.dist-info/RECORD
