Metadata-Version: 2.1
Name: magali
Version: 0.0.post13
Summary: Modelling and inversion of magnetic microscopy data
Home-page: https://github.com/compgeolab/magali
Maintainer: Leonardo Uieda
Maintainer-email: leouieda@gmail.com
License: MIT License
Project-URL: Documentation, https://www.compgeolab.org/magali
Project-URL: Release Notes, https://github.com/compgeolab/magali/releases
Project-URL: Bug Tracker, https://github.com/compgeolab/magali/issues
Project-URL: Source Code, https://github.com/compgeolab/magali
Keywords: xarray,magnetic,microscopy,geophysics,paleomagnetism
Platform: any
Classifier: Development Status :: 3 - Alpha
Classifier: Intended Audience :: Science/Research
Classifier: Intended Audience :: Developers
Classifier: Intended Audience :: Education
Classifier: Natural Language :: English
Classifier: Operating System :: OS Independent
Classifier: Topic :: Scientific/Engineering
Classifier: Topic :: Software Development :: Libraries
Classifier: Programming Language :: Python :: 3 :: Only
Classifier: Programming Language :: Python :: 3.7
Classifier: Programming Language :: Python :: 3.8
Classifier: Programming Language :: Python :: 3.9
Classifier: Programming Language :: Python :: 3.10
Requires-Python: >=3.7
License-File: LICENSE.txt
Requires-Dist: numpy (>=1.19)
Requires-Dist: xarray (>=0.16)
Requires-Dist: scikit-image (>=0.18)
Requires-Dist: harmonica (>=0.6)
Requires-Dist: verde (>=1.7)
Requires-Dist: choclo (>=0.0.1)
